{
  "eoc": 30,
  "offer_price": 80,
  "diff_per": 60,
  "off_per":60,
  "offer_per": 105,
  "dayp_offer_amt": 80,
  "offer": 60,
  "cert": 40,
  "shape": 45,
  "clarity": 50,
  "color": 40,
  "carat": 40,
  "dollarCt": 60,
  "off": 45,
  "amount": 65,
  "cut": 35,
  "pol": 35,
  "sym": 35,
  "fluor": 40,
  "measurement": 115,
  "dr": 35,
  "tab": 35,
  "td": 40,
  "shd": 40,
  "lus": 40,
  "tw": 40,
  "sw": 40,
  "tb": 40,
  "sb": 40,
  "sgs": 380,
  "ts": 30,
  "ss": 30,
  "to": 30,
  "po": 30,
  "co": 30,
  "go": 30,
  "tef": 40,
  "pef": 40,
  "cef": 40,
  "kts": 350,
  "lab": 150,
  "girdle": 65,
  "ha": 50,
  "certNo": 80,
  "rap": 70,
  "eligible": 100,
  "wvd": 50,
  "coop": 60,
  "online_per": 65,
  "final_price": 60,
  "final_off": 60,
  "event": 65,
  "final_amount": 90,
  "term": 65
}
